README
setup.py
PyPalm.egg-info/PKG-INFO
PyPalm.egg-info/SOURCES.txt
PyPalm.egg-info/dependency_links.txt
PyPalm.egg-info/entry_points.txt
PyPalm.egg-info/top_level.txt
pypalm/__init__.py
pypalm/basic.py
pypalm/generate.py
pypalm/lang.py
pypalm/pypalm.py