Metadata-Version: 1.0
Name: PyPalm
Version: 0.20.17
Summary: PyPalm should ease handling the development of Palm WebOs applications
Home-page: http://github.com/grundprinzip/PyPalm
Author: Martin Grund
Author-email: grundprinzip@gmail.com
License: UNKNOWN
Platform: UNKNOWN
